{
"type": "FeatureCollection",
"crs": { "type": "name", "properties": { "name": "urn:ogc:def:crs:OGC:1.3:CRS84" } },
                                                                                
"features": [
{ "type": "Feature", "properties": { "src_date": null, "src_info": null, "act_id": "EMSR-921", "ext_scale": "10k", "nam": "Dobrich", "ext_date": null, "txt": "city", "subtype": "ZD040 - Named Location", "admin_lev": "populated place", "source_nam": "Open Street Map" }, "geometry": { "type": "Point", "coordinates": [ 27.829741507999902, 43.568839713994521 ] } },
{ "type": "Feature", "properties": { "src_date": null, "src_info": null, "act_id": "EMSR-921", "ext_scale": "10k", "nam": "Druzhba 1", "ext_date": null, "txt": "suburb", "subtype": "ZD040 - Named Location", "admin_lev": "populated place", "source_nam": "Open Street Map" }, "geometry": { "type": "Point", "coordinates": [ 27.84506541499994, 43.567331328994541 ] } },
{ "type": "Feature", "properties": { "src_date": null, "src_info": null, "act_id": "EMSR-921", "ext_scale": "10k", "nam": "Balik", "ext_date": null, "txt": "suburb", "subtype": "ZD040 - Named Location", "admin_lev": "populated place", "source_nam": "Open Street Map" }, "geometry": { "type": "Point", "coordinates": [ 27.848826884999912, 43.575182929994504 ] } },
{ "type": "Feature", "properties": { "src_date": null, "src_info": null, "act_id": "EMSR-921", "ext_scale": "10k", "nam": "Dobrotitsa", "ext_date": null, "txt": "suburb", "subtype": "ZD040 - Named Location", "admin_lev": "populated place", "source_nam": "Open Street Map" }, "geometry": { "type": "Point", "coordinates": [ 27.830735265999898, 43.552629604994536 ] } },
{ "type": "Feature", "properties": { "src_date": null, "src_info": null, "act_id": "EMSR-921", "ext_scale": "10k", "nam": "Lozyata", "ext_date": null, "txt": "suburb", "subtype": "ZD040 - Named Location", "admin_lev": "populated place", "source_nam": "Open Street Map" }, "geometry": { "type": "Point", "coordinates": [ 27.815517276999948, 43.554971932994533 ] } },
{ "type": "Feature", "properties": { "src_date": null, "src_info": null, "act_id": "EMSR-921", "ext_scale": "10k", "nam": "Hristo Botev", "ext_date": null, "txt": "suburb", "subtype": "ZD040 - Named Location", "admin_lev": "populated place", "source_nam": "Open Street Map" }, "geometry": { "type": "Point", "coordinates": [ 27.841480910999937, 43.573940202994528 ] } },
{ "type": "Feature", "properties": { "src_date": null, "src_info": null, "act_id": "EMSR-921", "ext_scale": "10k", "nam": "Druzhba 2", "ext_date": null, "txt": "suburb", "subtype": "ZD040 - Named Location", "admin_lev": "populated place", "source_nam": "Open Street Map" }, "geometry": { "type": "Point", "coordinates": [ 27.846420734999899, 43.564336403994552 ] } },
{ "type": "Feature", "properties": { "src_date": null, "src_info": null, "act_id": "EMSR-921", "ext_scale": "10k", "nam": "Druzhba 4", "ext_date": null, "txt": "suburb", "subtype": "ZD040 - Named Location", "admin_lev": "populated place", "source_nam": "Open Street Map" }, "geometry": { "type": "Point", "coordinates": [ 27.847348719999932, 43.560877277994557 ] } },
{ "type": "Feature", "properties": { "src_date": null, "src_info": null, "act_id": "EMSR-921", "ext_scale": "10k", "nam": "Druzhba 3", "ext_date": null, "txt": "suburb", "subtype": "ZD040 - Named Location", "admin_lev": "populated place", "source_nam": "Open Street Map" }, "geometry": { "type": "Point", "coordinates": [ 27.841354071999923, 43.559708415994514 ] } }
]
}
